{"biodiversity dimensions": ["variable", "4e366444-01ea-4517-9d93-56f55ddf41b7", "BIODIVERSITY FUNCTIONS", 0.5015192253578344], "climate change mitigation measures": ["variable", "c4a6c571-406e-4023-b479-6a1fc30f184c", "CLIMATE MITIGATION", 0.5579821332317609], "reforestation activities": ["variable", "be7f6de0-f51e-42bc-9a66-fff30d809a67", "REFORESTATION", 0.5066478935229414], "climate change response measures": ["variable", "f69374fe-eda2-4223-b130-096220251235", "GLOBAL CHANGE RESPONSES", 0.5151055635534265], "afforestation": ["variable", "a28eeef3-b252-4309-957b-860d2e0f97ef", "AFFORESTATION/REFORESTATION", 0.5808823048581611], "biosphere": ["variable", "91c64c46-d040-4daa-b26c-61952fdfaf50", "BIOSPHERE", 0.50935601799197], "capture and geological storage": ["variable", "e8c24822-7d2d-48c6-9dca-df3860e9bd63", "CARBON CAPTURE AND STORAGE", 0.5209604606579911], "environmental sustainability": ["variable", "73266dd6-217a-432f-9237-176d3e94b39b", "ENVIRONMENTAL SUSTAINABILITY", 0.5365300106141183], "HCFC-22": ["variable", "f2464ebf-811a-43c2-bd50-9e80e03e07b3", "HCFC-22", 0.5829816068928209], "climate change mitigation efforts": ["variable", "c4a6c571-406e-4023-b479-6a1fc30f184c", "CLIMATE MITIGATION", 0.5218394895697178], "environmental governance": ["variable", "d81b77be-0177-4e26-942c-aa911239482d", "ENVIRONMENTAL GOVERNANCE/MANAGEMENT", 0.5414454917595523], "climate change mitigation problems": ["variable", "c4a6c571-406e-4023-b479-6a1fc30f184c", "CLIMATE MITIGATION", 0.5081052362737714], "negative environmental impacts": ["variable", "3f4cfc81-7745-43d9-b313-f68cdf72359b", "ENVIRONMENTAL IMPACTS", 0.5181507341327822], "overall environmental sustainability": ["variable", "73266dd6-217a-432f-9237-176d3e94b39b", "ENVIRONMENTAL SUSTAINABILITY", 0.5176145804094825], "food security": ["variable", "85a73755-cb84-40cb-a23e-2ed3811138f8", "FOOD SECURITY", 0.5013138388957085], "UNFCCC regime": ["project", "67f93e65-5991-4ffa-85ec-a26bd324181e", "UNFCCC", 0.5050551936058673], "water resources": ["variable", "ee3e296f-fdc0-4695-95af-dbe63f43b679", "WATER RESOURCES", 0.5368902108321312], "UNFCCC Secretariat": ["provider", "7471c405-d062-42cb-bfab-94a93d46cce6", "UNFCCC", 0.5029378932228481], "climate change mitigation": ["variable", "c4a6c571-406e-4023-b479-6a1fc30f184c", "CLIMATE MITIGATION", 0.5406246526489308], "IPCC, carbon dioxide capture": ["variable", "e8c24822-7d2d-48c6-9dca-df3860e9bd63", "CARBON CAPTURE AND STORAGE", 0.5073933034839986], "hydrofluorocarbons": ["variable", "ed5106fd-a73f-4203-87a3-9c9e7e85dcfc", "HYDROFLUOROCARBONS", 0.5871871532395554], "sulphur hexafluoride": ["variable", "b4c7dec8-6a9a-4424-8f80-4ad1ed0bc5ec", "SULFUR HEXAFLUORIDE", 0.6220567685704012], "environmental impacts": ["variable", "3f4cfc81-7745-43d9-b313-f68cdf72359b", "ENVIRONMENTAL IMPACTS", 0.5295764968393984], "land tenure": ["variable", "0ceb5ef1-5a07-4f93-8e86-d3cc2baf5768", "LAND TENURE", 0.5085462538070719], "invasive alien species": ["variable", "7bfdbe8d-3945-4678-a90b-d2251f973955", "INVASIVE SPECIES", 0.560577407044944], "UNFCCC Secretariat's website": ["provider", "7471c405-d062-42cb-bfab-94a93d46cce6", "UNFCCC", 0.5161574092505208], "UNFCCC regimes": ["project", "67f93e65-5991-4ffa-85ec-a26bd324181e", "UNFCCC", 0.5130498335535217], "hydrocarbons": ["variable", "344cbd30-a2e4-437e-9fc9-5e6b1c484bac", "HYDROCARBONS", 0.5193384764711494], "climate change mitigation and adaptation actions": ["variable", "c4a6c571-406e-4023-b479-6a1fc30f184c", "CLIMATE MITIGATION", 0.5012145514860121], "deforestation": ["variable", "9a4715a7-1847-4fef-8116-494b36420fb7", "DEFORESTATION", 0.5203924226860277]}