{"hailstorms)-Differences": ["weather event", "a2ea1792-c011-4c7c-95c7-3bd648b1b57b", "HAIL STORMS", 0.5241992974958493], "Extreme precipitation": ["variable", "fc5a1b7a-5ee8-4d67-80f5-a57e3f1734ab", "EXTREME PRECIPITATION", 0.5527400868042711], "extreme precipitation trends": ["variable", "fc5a1b7a-5ee8-4d67-80f5-a57e3f1734ab", "EXTREME PRECIPITATION", 0.5492113763816071], "Sulfate aerosol concentration": ["variable", "ca71b02b-4446-414c-8697-0950d7382cc4", "SULFATE PARTICLES", 0.5360824444400409], "tropical cyclones": ["weather event", "06180441-d4bb-4fed-b36a-9b3cb2cac0fe", "TROPICAL CYCLONES", 0.5758487319105177], "extreme precipitation metrics": ["variable", "fc5a1b7a-5ee8-4d67-80f5-a57e3f1734ab", "EXTREME PRECIPITATION", 0.5867413208473211], "thermohaline circulation variability": ["ocean circulation", "aa1bc71c-daeb-401e-9e29-ebde975482cf", "THERMOHALINE CIRCULATION", 0.6055358965040816], "abundant atmospheric water vapor": ["variable", "286d2ae0-9d86-4ef0-a2b4-014843a98532", "ATMOSPHERIC WATER VAPOR", 0.5729015650226899], "decadal-scale variability": ["experiment", "addadf3e-ae8d-49aa-9b5d-abee1952a543", "decadal", 0.6168840679227117], "water vapor trends": ["variable", "5cd8b242-ac18-4d9f-85d5-eb551792d7e9", "WATER VAPOR TENDENCY", 0.5439990895851684], "actual severe weather events": ["variable", "0d67baa7-19c7-440b-b658-1bda9a8e09bf", "SEVERE WEATHER", 0.5148932302133745], "extreme precipitation rates": ["variable", "fc5a1b7a-5ee8-4d67-80f5-a57e3f1734ab", "EXTREME PRECIPITATION", 0.5704605867488683], "extreme weather": ["variable", "b29b46ad-f05f-4144-b965-5f606ce96963", "EXTREME WEATHER", 0.5095324887719406], "mesoscale convective systems": ["variable", "d13661da-d022-439a-bb27-dc2273f9dc88", "MESOSCALE CONVECTIVE COMPLEX", 0.5114172480354915], "decadal changes": ["experiment", "addadf3e-ae8d-49aa-9b5d-abee1952a543", "decadal", 0.562491143526431], "orographic forcing": ["variable", "84780569-bef5-41fd-901f-828418e390dd", "OROGRAPHIC LIFTING", 0.5478692378887057], "severe thunderstorm occurrence": ["natural hazard", "ad28623e-bb9b-433c-8fc1-2ab06dda58c4", "SEVERE STORMS", 0.5009859466691217], "typhoons-Robust detection": ["natural hazard", "bd5c19e4-b25a-48b2-ad9d-4596a0ba67de", "TYPHOONS", 0.5029166254029235], "western North Pacific typhoons": ["weather event", "09849cf3-df4d-40d3-a224-f30c6fe22c1f", "TYPHOONS (WESTERN N. PACIFIC)", 0.5389474634662956], "surface wind speed": ["variable", "c65a5d81-6dd6-4013-828d-5060c8569b63", "sfcWind", 0.5305150206479318], "severe thunderstorm environments": ["natural hazard", "ad28623e-bb9b-433c-8fc1-2ab06dda58c4", "SEVERE STORMS", 0.511401400887388], "Frozen precipitation": ["variable", "d57a7ba2-7d23-472f-8d6c-674dec4e8fa0", "FROZEN PRECIPITATION", 0.5161634470257074], "Arabian Sea": ["location", "a186eed4-d1b4-4d11-b218-b61708a9124c", "ARABIAN SEA", 0.5291245409645859], "severe convective storms": ["natural hazard", "ad28623e-bb9b-433c-8fc1-2ab06dda58c4", "SEVERE STORMS", 0.5200299803110867], "coterminous United States": ["location", "e5e56286-ef79-45ac-af70-05ab0696ac1c", "contiguous_united_states", 0.5055311136180184], "observed decadal variability": ["experiment", "addadf3e-ae8d-49aa-9b5d-abee1952a543", "decadal", 0.5091811552625615], "ENSO behavior": ["teleconnection", "095a05c0-6220-4abd-9c1b-c4504a092d7d", "EL NINO SOUTHERN OSCILLATION (ENSO)", 0.5030338077544667], "Freezing rain climatologies": ["variable", "a90306f0-353c-4083-941a-0973a6fd6584", "FREEZING RAIN", 0.5101549058882917], "extreme precipitation": ["variable", "fc5a1b7a-5ee8-4d67-80f5-a57e3f1734ab", "EXTREME PRECIPITATION", 0.5959445011655629], "global climate model simulations": ["platform", "8680cb49-1637-4a47-a5fd-f39d4e618e45", "CLIMATE MODELS", 0.5120315960305589], "1) severe convective storms": ["natural hazard", "ad28623e-bb9b-433c-8fc1-2ab06dda58c4", "SEVERE STORMS", 0.5805063170639138], "decadal periods": ["variable", "3d97e993-dc6a-41ff-8a49-3e837c1fc2b1", "Decadal", 0.5550491418366866], "atmospheric water vapor": ["variable", "286d2ae0-9d86-4ef0-a2b4-014843a98532", "ATMOSPHERIC WATER VAPOR", 0.6393048535526921], "hailstorms": ["weather event", "a2ea1792-c011-4c7c-95c7-3bd648b1b57b", "HAIL STORMS", 0.5057804603231716], "extratropical cyclones": ["weather event", "da436e9b-60e5-4a5f-a50a-08794d62bca8", "EXTRATROPICAL CYCLONES", 0.6238241720282086], "tropical cyclone tracks": ["weather event", "10a9bb22-9119-4409-84c1-7c97ef31b1a1", "TROPICAL CYCLONE TRACK", 0.5432514386807046], "multidecadal or longer time scales": ["variable", "3d97e993-dc6a-41ff-8a49-3e837c1fc2b1", "Decadal", 0.5284951091558607], "extreme precipitation events": ["variable", "fc5a1b7a-5ee8-4d67-80f5-a57e3f1734ab", "EXTREME PRECIPITATION", 0.6021201182463329], "increasing atmospheric water vapor": ["variable", "286d2ae0-9d86-4ef0-a2b4-014843a98532", "ATMOSPHERIC WATER VAPOR", 0.5498014415425199], "precipitation-producing systems": ["variable", "ca7f5dbd-199e-4cc8-bc7b-550753ecbc93", "PRECIPITATING CONVECTIVE CLOUD SYSTEMS", 0.524861934463489], "tropical cyclone frequency": ["weather event", "de9ffa22-76e3-469c-926b-2dee007702d0", "TROPICAL STORM FREQUENCY", 0.5550662716490398], "considerable decadal-scale variability": ["experiment", "addadf3e-ae8d-49aa-9b5d-abee1952a543", "decadal", 0.5170996835086868], "global climate models": ["platform", "8680cb49-1637-4a47-a5fd-f39d4e618e45", "CLIMATE MODELS", 0.5389863325269199], "liquid precipitation": ["variable", "7d45f108-dda2-4341-b853-ee3a490aad59", "LIQUID PRECIPITATION", 0.6120942429870513], "single extreme precipitation event": ["variable", "fc5a1b7a-5ee8-4d67-80f5-a57e3f1734ab", "EXTREME PRECIPITATION", 0.5417318319180117], "severe weather conditions": ["variable", "0d67baa7-19c7-440b-b658-1bda9a8e09bf", "SEVERE WEATHER", 0.534552415885359], "teleconnections": ["variable", "b887d3e5-4280-43d2-a34e-0f63ac086b6a", "TELECONNECTIONS", 0.594727644124143], "North Atlantic Oscillation": ["teleconnection", "c5e1c055-768e-4aa3-a0a1-3adfda8ecdca", "NORTH ATLANTIC OSCILLATION", 0.660285180728043], "western United States": ["location", "de433636-5ea1-47b0-9b86-95e081eefab4", "WESTERN UNITED STATES", 0.5577884487898641], "water vapor": ["variable", "15029eb0-6342-4066-8ac9-c50f7dbfb392", "WATER VAPOR", 0.5250797031203547], "social vulnerability": ["variable", "33f20afe-5ce2-43e9-9676-c5f664fbc324", "VULNERABILITY LEVELS/INDEX", 0.5135625245514467], "severe weather warning process": ["variable", "0d67baa7-19c7-440b-b658-1bda9a8e09bf", "SEVERE WEATHER", 0.514661224716289], "extreme precipitation totals": ["variable", "fc5a1b7a-5ee8-4d67-80f5-a57e3f1734ab", "EXTREME PRECIPITATION", 0.5658034144244498], "severe and nonsevere thunderstorms": ["natural hazard", "ad28623e-bb9b-433c-8fc1-2ab06dda58c4", "SEVERE STORMS", 0.5110476165870106], "Global Historical Climate Networkdaily": ["project", "c3e53b0d-cf82-4d03-ba0e-5544b99ad238", "GHCN", 0.5875520476192773], "sulfate aerosols": ["variable", "ca71b02b-4446-414c-8697-0950d7382cc4", "SULFATE PARTICLES", 0.5928009387595675], "tropical cyclone intensity": ["weather event", "06180441-d4bb-4fed-b36a-9b3cb2cac0fe", "TROPICAL CYCLONES", 0.5088832491586711], "cloud albedo": ["variable", "34e4bf15-fa75-409a-bac2-8ddfe8e7fe75", "albedo", 0.5873486683977037], "tropical cyclone activity": ["weather event", "06180441-d4bb-4fed-b36a-9b3cb2cac0fe", "TROPICAL CYCLONES", 0.5254013271430559], "convective and nonconvective precipitation": ["variable", "a42f94f5-1ba2-45cd-ad2a-ca3468efc35e", "convective_precipitation", 0.5696544362902435], "contiguous United States": ["location", "e5e56286-ef79-45ac-af70-05ab0696ac1c", "contiguous_united_states", 0.6090843015652162], "aerosols": ["variable", "2e5a401b-1507-4f57-82b8-36557c13b154", "AEROSOLS", 0.504198919698992], "snow and water content": ["variable", "a5279e80-7d3d-434e-b9d4-a0a96ace80a1", "LIQUID WATER CONTENT", 0.5084242937215976], "scatterometer coverage": ["instrument", "2ea0f679-bb41-4a04-b9b5-d6786ecaa5cb", "SCATTEROMETERS", 0.5351531795619439], "storm frequency undercounts": ["weather event", "de9ffa22-76e3-469c-926b-2dee007702d0", "TROPICAL STORM FREQUENCY", 0.5055757012445166], "water vapor concentration": ["variable", "04c30b59-88ea-4311-8353-8896d4eba83f", "WATER VAPOR CONCENTRATION PROFILES", 0.5619384688116005]}