{"tornado occurrence": ["weather event", "de691f09-0ef3-4795-bac0-1ed15c3e7f8b", "TORNADO FREQUENCY", 0.5066293233056267], "diurnal cycle": ["variable", "99ef187e-6940-4c10-8d65-00d4426d493b", "Diurnal", 0.5730121371169531], "Madden-Julian Oscillation": ["teleconnection", "25d4368e-3b66-40d5-bac1-2343b127fa32", "MADDEN-JULIAN OSCILLATION", 0.6681288960397864], "0-1 km bulk vertical wind shear": ["variable", "1b0abf68-b069-4a0b-8081-35a36da9d4a7", "VERTICAL WIND SHEAR", 0.5132267614129283], "El Nino-Southern Oscillation": ["teleconnection", "095a05c0-6220-4abd-9c1b-c4504a092d7d", "EL NINO SOUTHERN OSCILLATION (ENSO)", 0.6214142269543312], "precipitation extremes": ["variable", "fc5a1b7a-5ee8-4d67-80f5-a57e3f1734ab", "EXTREME PRECIPITATION", 0.516897561981213], "regional tornado frequency": ["weather event", "de691f09-0ef3-4795-bac0-1ed15c3e7f8b", "TORNADO FREQUENCY", 0.5733628357748741], "convective cloud tops": ["variable", "c036679f-f295-4022-a2cd-f26ee8ec5829", "convective_cloud_top", 0.5574338870215825], "tropical cyclones": ["weather event", "06180441-d4bb-4fed-b36a-9b3cb2cac0fe", "TROPICAL CYCLONES", 0.5758487319105177], "diurnal variability": ["variable", "99ef187e-6940-4c10-8d65-00d4426d493b", "Diurnal", 0.5183374365451757], "SPC Severe Weather Database": ["provider", "0f588bb4-6e45-4d42-af5c-2801b6a4ef6e", "DOC/NOAA/NWS/NCEP/SPC", 0.526962989849734], "atmospheric instability": ["variable", "ff5d5c12-74d9-435d-9164-1c9d69f967d7", "ATMOSPHERIC STABILITY", 0.5191266720653851], "global reanalysis": ["variable", "878e70de-f929-4d2f-9325-145ca95787e9", "reanalysis", 0.5881789361924511], "radar reflectivity": ["variable", "46975e66-863a-49c9-b673-b2e099a04c85", "RADAR REFLECTIVITY", 0.5289791377944262], "storm relative helicity": ["variable", "185b86e2-af35-42b2-b20d-f9ca6fdab493", "STORM RELATIVE WINDS", 0.5419625702690019], "tornado environment frequency": ["weather event", "de691f09-0ef3-4795-bac0-1ed15c3e7f8b", "TORNADO FREQUENCY", 0.6072990797806777], "cloud microphysics": ["variable", "0cfcbaa7-727b-4199-8cca-93824b427e9b", "CLOUD MICROPHYSICS", 0.6259515460265617], "freezing level": ["variable", "4904c803-4d8a-4c15-aae7-67eea1fa1ab3", "freezing_level", 0.5400976529420457], "tornado environment index": ["natural hazard", "ff44a7b0-64b6-418a-9d74-1cbc3a4ae951", "TORNADOES", 0.5027677683550418], "10 GCM CMIP5 projections": ["project", "f4bc60f4-5505-4eb4-83e6-585e0683eac3", "CMIP 5", 0.5030565883895919], "decreased vertical wind shear": ["variable", "1b0abf68-b069-4a0b-8081-35a36da9d4a7", "VERTICAL WIND SHEAR", 0.5020570651169378], "climate variables": ["variable", "160af7da-6036-4af5-ba04-d666df8a0daa", "Variables", 0.5443447528318661], "global SST": ["experiment", "0d5ab635-8ada-4933-80e5-dc77a4548dfd", "spinup-1950", 0.5251436024476008], "interannual, and multidecadal variability": ["experiment", "addadf3e-ae8d-49aa-9b5d-abee1952a543", "decadal", 0.5003510084182843], "warming climate": ["variable", "49d638f4-bdfa-4a6e-b154-cce1717d307f", "CLIMATE WARMING", 0.5016964405999075], "ERA-40 reanalysis": ["variable", "3658db7a-74a2-4614-bb3c-7d0eef569aa5", "ERA-40", 0.6603865867867452], "monthly climatology": ["variable", "8c8c70b1-f6c5-4f34-89b5-510049b8c8ab", "Monthly Climatology", 0.5621759539953627], "atmospheric aerosols": ["variable", "2e5a401b-1507-4f57-82b8-36557c13b154", "AEROSOLS", 0.5726296677892637], "National Lightning Detection Network": ["platform", "081f2d22-ca33-437f-b945-57397fd24247", "NLDN", 0.5232317613190897], "hail events": ["weather event", "a2ea1792-c011-4c7c-95c7-3bd648b1b57b", "HAIL STORMS", 0.5206922068418548], "Rossby waves": ["variable", "41764af0-1264-4adb-881d-44991489344c", "ROSSBY/PLANETARY WAVES", 0.518934734948545], "severe weather occurrence information": ["variable", "0d67baa7-19c7-440b-b658-1bda9a8e09bf", "SEVERE WEATHER", 0.5318590988132968], "radiatively forced climate change": ["variable", "4fad64ce-32fe-413d-8b55-c78000d1980c", "RADIATIVE FORCING", 0.5515237904720565], "ENSO signal": ["teleconnection", "095a05c0-6220-4abd-9c1b-c4504a092d7d", "EL NINO SOUTHERN OSCILLATION (ENSO)", 0.5199505611571088], "real-time multivariate MJO indices": ["teleconnection", "caddaef6-1a60-490a-938e-9107885f286f", "MULTIVARIATE ENSO INDEX", 0.5295055582350038], "severe weather": ["variable", "0d67baa7-19c7-440b-b658-1bda9a8e09bf", "SEVERE WEATHER", 0.5110356128901786], "lapse rate": ["variable", "090697f0-a982-4cda-94f6-9375d0c816c5", "temperature_lapse_rate", 0.531867628421934], "remote sensing data sets": ["provider", "afa11694-6aad-4d0b-8588-5ae14cce35cc", "UID/CNR/RS-GISRL", 0.501269193225613], "population density": ["variable", "d2a5c7ec-ccf2-4ab7-8863-9063be91c022", "POPULATION DENSITY", 0.5273828218434097], "convective precipitation": ["variable", "a42f94f5-1ba2-45cd-ad2a-ca3468efc35e", "convective_precipitation", 0.6525091078015557], "deep convective storms": ["variable", "879cccd4-d375-40f6-8bee-6f58efd2dd61", "DEEP CONVECTIVE CLOUD SYSTEMS", 0.5349226070238724], "convective available potential energy": ["weather event", "00748b19-30cc-4d12-a7a3-0aa8b3be5a94", "CONVECTIVE AVAILABLE POTENTIAL ENERGY (CAPE)", 0.5492429873314876], "tropical cyclone frequency": ["weather event", "de9ffa22-76e3-469c-926b-2dee007702d0", "TROPICAL STORM FREQUENCY", 0.5550662716490398], "vertical wind shear": ["variable", "1b0abf68-b069-4a0b-8081-35a36da9d4a7", "VERTICAL WIND SHEAR", 0.5735030689963969], "severe thunderstorm environments": ["natural hazard", "ad28623e-bb9b-433c-8fc1-2ab06dda58c4", "SEVERE STORMS", 0.511401400887388]}